patmanu/README.rst
patmanu/__init__.py
patmanu/__main__.py
patmanu/checkpatch.py
patmanu/commit.py
patmanu/control.py
patmanu/func_test.py
patmanu/get_maintainer.py
patmanu/gitutil.py
patmanu/patchstream.py
patmanu/patman.rst
patmanu/project.py
patmanu/series.py
patmanu/settings.py
patmanu/setup.py
patmanu/status.py
patmanu/test_checkpatch.py
patmanu/test_settings.py
patmanu-0.0.1.dist-info/LICENSE
patmanu-0.0.1.dist-info/METADATA
patmanu-0.0.1.dist-info/WHEEL
patmanu-0.0.1.dist-info/entry_points.txt
patmanu-0.0.1.dist-info/top_level.txt
patmanu-0.0.1.dist-info/RECORD
