Metadata-Version: 2.1
Name: patmanu
Version: 0.0.1
Summary: Patman patch manager
Author-email: Simon Glass <sjg@chromium.org>
Project-URL: Homepage, https://u-boot.readthedocs.io/en/latest/develop/patman.html
Project-URL: Bug Tracker, https://source.denx.de/groups/u-boot/-/issues
Classifier: Programming Language :: Python :: 3
Classifier: License :: OSI Approved :: GNU General Public License v2 or later (GPLv2+)
Classifier: Operating System :: OS Independent
Requires-Python: >=3.7
License-File: LICENSE
Requires-Dist: u-boot-pylib
